{
  "version": 8,
  "name": "Campusmedius Topology",
  "metadata": {
  },
    "sources": {
      "eckebrecht": {
            "type": "image",
            "url": "./assets/eckebrecht.jpg",
            "coordinates":
            [
                [-180, 85],
                [180, 85],
                [180, -85],
                [-180, -85]
            ]
},
        "vienna1933": {
                    "type": "raster",
                    "tiles": [
                        "https://campusmedius.net/tiles/{z}/{x}/{y}.png"
                    ],
                    "tileSize": 512,
                    "scheme": "tms",
                    "minzoom": 9,
                    "maxzoom": 17
                }
    },
    "layers": [
        {
            "id": "vienna1933",
            "type": "raster",
            "source": "vienna1933"
        },
        {
            "id": "eckebrecht",
            "type": "raster",
            "source": "eckebrecht",
            "layout": {
                "visibility": "none"
            }
        }
  ],
  "id": "cm-topology"
}
